django_querycache/__init__.py
django_querycache/cacheman.py
django_querycache/drf_mixins.py
django_querycache/fingerprinting.py
django_querycache/hashfunctions.py
django_querycache/type_annotations.py
django_querycache/utils.py
django_querycache-0.3.0.dist-info/LICENSE
django_querycache-0.3.0.dist-info/METADATA
django_querycache-0.3.0.dist-info/WHEEL
django_querycache-0.3.0.dist-info/RECORD
