Metadata-Version: 2.1
Name: django-querycache
Version: 0.3.0
Summary: Cache manager for Django querysets and serialization
License: GPLv3
Author: Joshua Brooks
Author-email: josh.vdbroek@gmail.com
Requires-Python: >=3.8.1
Classifier: License :: Other/Proprietary License
Classifier: Programming Language :: Python :: 3
Classifier: Programming Language :: Python :: 3.9
Classifier: Programming Language :: Python :: 3.10
Classifier: Programming Language :: Python :: 3.11
